{"views_application_rust_rust-base.md":"0d5342e7","api-examples.md":"24b4dc4e","views_application_node-cpp.md":"b077e589","index.md":"e88afc82","markdown-examples.md":"d4e9062e","views_backend_node-crawl.md":"49a46a43","views_backend_midway.md":"e6d6a731","views_frontend_drag.md":"e13c0e41","views_frontend_electron-builder.md":"da2c19c1","views_application_your-first-extension.md":"cff2ad1d","views_frontend_canvas.md":"b8a7637f","views_frontend_js-base.md":"b4ae1432","views_backend_node-excel.md":"eb485e89","views_frontend_hammerjs.md":"bafc21c6","views_backend_third-table.md":"4b047667","views_frontend_excel.md":"fd3bb91e","views_frontend_indexdb.md":"6990f9e5","views_application_electron-sqlite.md":"8a46962c","views_backend_node-word.md":"a7c68005","views_backend_node-esm.md":"4bfd0097","views_backend_node-tensorflow.md":"f1dc3ffa","views_frontend_algorithms.md":"409a69da","views_backend_node-child_process.md":"71f3edee","views_application_rust_rust-lib.md":"d8d822c5","views_techstack_method-plug.md":"54a13830","views_techstack_docker.md":"51c8b522","views_application_vscode-debug.md":"0c5dc40a","views_frontend_react_react-quick-start.md":"2da98b2f","views_frontend_qiankun-vite.md":"fe111e0b","views_application_rust_rust-node.md":"8e2d9728","views_frontend_ellipsis-text.md":"b8fefb20","views_frontend_file-slice.md":"afc3c270","views_frontend_tailwind.md":"d6ced2b3","views_frontend_react_react-practice.md":"ca881a99","views_frontend_stylecollection.md":"af412aa6","views_application_rust_rust-wasm.md":"2edbd9b3","views_application_electron-rebuild.md":"f2d32b1b","views_frontend_word.md":"58a168a2","views_frontend_clickoutside.md":"5f2ae9c0","views_frontend_face-api.md":"d4a7c047","views_frontend_vue_vue-ref.md":"dae974e9","views_techstack_nginx.md":"64426f2f","views_frontend_vue-drag.md":"6c3c3af3","views_frontend_web-animation-api.md":"95a0aa42","views_frontend_webcomponent.md":"a4a7f2f0","views_techstack_bat.md":"c08e2e68","views_techstack_bit-operate.md":"9141faed","views_frontend_vue_vue-sourcecode.md":"6d8d89cb","views_techstack_vim-operate.md":"b5944f05","views_application_electron.md":"c86885c6","views_frontend_css-ball.md":"b933dcf5","views_frontend_viteconfig.md":"2a905e78","views_frontend_async-infect.md":"fcc4a288","views_frontend_typescript_type-error.md":"44047cf6","views_frontend_vue-to-pdf.md":"ba7aca8b","views_frontend_tsconfig-detail.md":"3e7c8591","views_frontend_chrome-extension.md":"719f5e23","views_backend_task-manager.md":"6cdba2de","views_techstack_linux.md":"b551d035","views_techstack_mac.md":"93f8ec49","views_techstack_dailynote.md":"927ed574","views_techstack_navicat.md":"b26be276","views_frontend_vue_component-lib.md":"5fb32344","views_frontend_react_react-skill.md":"ef0930ca","views_frontend_wx-formdata.md":"ec6f983e"}
